nunchaku_chroma/__init__.py
nunchaku_chroma/transformer_chroma.py
nunchaku_chroma/comfyui/__init__.py
nunchaku_chroma/comfyui/loader.py
nunchaku_chroma/comfyui/lora.py
nunchaku_chroma/comfyui/wrapper.py
nunchaku_chroma/lora/__init__.py
nunchaku_chroma/lora/compose.py
nunchaku_chroma/lora/diffusers_converter.py
nunchaku_chroma/lora/nunchaku_converter.py
nunchaku_chroma-0.1.3.dist-info/licenses/LICENSE
nunchaku_chroma-0.1.3.dist-info/METADATA
nunchaku_chroma-0.1.3.dist-info/WHEEL
nunchaku_chroma-0.1.3.dist-info/top_level.txt
nunchaku_chroma-0.1.3.dist-info/RECORD
