Metadata-Version: 2.4
Name: nunchaku-chroma
Version: 0.1.3
Summary: Chroma model support for Nunchaku - quantized inference for diffusion models
Author: spooknik
License: Apache-2.0
Project-URL: Homepage, https://github.com/spooknik/nunchaku-chroma
Project-URL: Repository, https://github.com/spooknik/nunchaku-chroma
Project-URL: Issues, https://github.com/spooknik/nunchaku-chroma/issues
Keywords: nunchaku,chroma,diffusion,quantization,comfyui
Classifier: Development Status :: 4 - Beta
Classifier: Intended Audience :: Developers
Classifier: License :: OSI Approved :: Apache Software License
Classifier: Programming Language :: Python :: 3
Classifier: Programming Language :: Python :: 3.10
Classifier: Programming Language :: Python :: 3.11
Classifier: Programming Language :: Python :: 3.12
Classifier: Topic :: Scientific/Engineering :: Artificial Intelligence
Requires-Python: >=3.10
License-File: LICENSE
Requires-Dist: nunchaku
Requires-Dist: torch>=2.0
Requires-Dist: diffusers>=0.32.0
Requires-Dist: einops
Requires-Dist: safetensors
Requires-Dist: huggingface-hub
Requires-Dist: numpy
Provides-Extra: dev
Requires-Dist: pytest; extra == "dev"
Requires-Dist: ruff; extra == "dev"
Dynamic: license-file
